simulation_alg-0.1.9.dist-info/METADATA
simulation_alg-0.1.9.dist-info/WHEEL
simulation_alg-0.1.9.dist-info/licenses/LICENSE
simulation/__init__.py
simulation/__init__.pyi
simulation/py.typed
simulation/simulation.cpython-312-x86_64-linux-gnu.so
simulation_alg-0.1.9.dist-info/RECORD
