Metadata-Version: 2.4
Name: simulation-alg
Version: 0.1.9
Classifier: Programming Language :: Rust
Classifier: Programming Language :: Python :: Implementation :: CPython
Classifier: Programming Language :: Python :: Implementation :: PyPy
License-File: LICENSE
Summary: A Python package for simulation algorithms
Home-Page: https://github.com/RaVincentHuang/simulation
License: MIT
Requires-Python: >=3.10
Project-URL: Source Code, https://github.com/RaVincentHuang/simulation
